<?xml version="1.0" encoding="UTF-8"?>
<!-- SPDX-License-Identifier: Apache-2.0 -->
<!-- (c) Copyright 2021 - 2022 Xilinx, Inc. All rights reserved. -->
<test name="basic" type="package">
  <objective>Basic tests</objective>
  <notes/>
  <iter result="PASSED">
    <notes/>
    <test name="driver_info" type="script">
      <objective>Check information returned about a driver for an interface.</objective>
      <notes/>
      <iter result="PASSED">
        <arg name="env"/>
        <notes/>
        <results tags="i40e&amp;linux-mm&gt;508" key="NO-MOD-VERSOIN" notes="intel/i40e module has no version information">
          <result value="PASSED">
            <verdict>Module i40e has no version information</verdict>
          </result>
        </results>
        <results tags="ice&amp;linux-mm&gt;508" key="NO-MOD-VERSOIN" notes="intel/ice module has no version information">
          <result value="PASSED">
            <verdict>Module ice has no version information</verdict>
          </result>
        </results>
        <results tags="igb&amp;linux-mm&gt;508" key="NO-MOD-VERSOIN" notes="igb module has no version information">
          <result value="PASSED">
            <verdict>Module igb has no version information</verdict>
          </result>
        </results>
        <results tags="mlx5_core&amp;linux-mm&gt;510" key="NO-MOD-VERSOIN">
          <result value="PASSED">
            <verdict>Module mlx5_core has no version information</verdict>
          </result>
        </results>
        <results tags="virtio-pci" key="NO-MOD-VERSOIN" notes="VirtIO net module has no version information">
          <result value="PASSED">
            <verdict>Module virtio_net has no version information</verdict>
          </result>
        </results>
      </iter>
    </test>
    <test name="rx_mode" type="script">
      <objective>Check that Rx mode is appropriately handled by the driver and packets are received or not depending on configured Rx mode and destination MAC address.</objective>
      <notes/>
      <iter result="PASSED">
        <arg name="env"/>
        <arg name="promisc"/>
        <arg name="allmulti"/>
        <notes/>
      </iter>
    </test>
    <test name="ethtool_reset_nic" type="script">
      <objective>Check what happens when NIC is reset with SIOCETHTOOL.</objective>
      <notes/>
      <iter result="PASSED">
        <arg name="env"/>
        <arg name="flag">none</arg>
        <arg name="sock_type"/>
        <arg name="if_down"/>
        <notes/>
        <results tags="i40e" key="NO-ETHTOOL-RESET" notes="intel/i40e does not support reset via ethtool">
          <result value="SKIPPED">
            <verdict>ETHTOOL_RESET is not supported</verdict>
          </result>
        </results>
        <results tags="ice" key="NO-ETHTOOL-RESET" notes="intel/ice does not support reset via ethtool">
          <result value="SKIPPED">
            <verdict>ETHTOOL_RESET is not supported</verdict>
          </result>
        </results>
        <results tags="igb" key="NO-ETHTOOL-RESET" notes="igb does not support reset via ethtool">
          <result value="SKIPPED">
            <verdict>ETHTOOL_RESET is not supported</verdict>
          </result>
        </results>
        <results tags="mlx5_core" key="NO-ETHTOOL-RESET" notes="mlx5_coredoes not support reset via ethtool">
          <result value="SKIPPED">
            <verdict>ETHTOOL_RESET is not supported</verdict>
          </result>
        </results>
        <results tags="virtio-pci" key="NO-ETHTOOL-RESET" notes="VirtIO net does not support reset via ethtool">
          <result value="SKIPPED">
            <verdict>ETHTOOL_RESET is not supported</verdict>
          </result>
        </results>
      </iter>
      <iter result="PASSED">
        <arg name="env"/>
        <arg name="flag">MAC</arg>
        <arg name="sock_type"/>
        <arg name="if_down"/>
        <notes/>
        <results tags="i40e" key="NO-ETHTOOL-RESET" notes="intel/i40e does not support reset via ethtool">
          <result value="SKIPPED">
            <verdict>ETHTOOL_RESET is not supported</verdict>
          </result>
        </results>
        <results tags="ice" key="NO-ETHTOOL-RESET" notes="intel/ice does not support reset via ethtool">
          <result value="SKIPPED">
            <verdict>ETHTOOL_RESET is not supported</verdict>
          </result>
        </results>
        <results tags="igb" key="NO-ETHTOOL-RESET" notes="igb does not support reset via ethtool">
          <result value="SKIPPED">
            <verdict>ETHTOOL_RESET is not supported</verdict>
          </result>
        </results>
        <results tags="mlx5_core" key="NO-ETHTOOL-RESET" notes="mlx5_coredoes not support reset via ethtool">
          <result value="SKIPPED">
            <verdict>ETHTOOL_RESET is not supported</verdict>
          </result>
        </results>
        <results tags="virtio-pci" key="NO-ETHTOOL-RESET" notes="VirtIO net does not support reset via ethtool">
          <result value="SKIPPED">
            <verdict>ETHTOOL_RESET is not supported</verdict>
          </result>
        </results>
      </iter>
      <iter result="PASSED">
        <arg name="env"/>
        <arg name="flag">DEDICATED</arg>
        <arg name="sock_type"/>
        <arg name="if_down"/>
        <notes/>
        <results tags="i40e" key="NO-ETHTOOL-RESET" notes="intel/i40e does not support reset via ethtool">
          <result value="SKIPPED">
            <verdict>ETHTOOL_RESET is not supported</verdict>
          </result>
        </results>
        <results tags="ice" key="NO-ETHTOOL-RESET" notes="intel/ice does not support reset via ethtool">
          <result value="SKIPPED">
            <verdict>ETHTOOL_RESET is not supported</verdict>
          </result>
        </results>
        <results tags="igb" key="NO-ETHTOOL-RESET" notes="igb does not support reset via ethtool">
          <result value="SKIPPED">
            <verdict>ETHTOOL_RESET is not supported</verdict>
          </result>
        </results>
        <results tags="mlx5_core" key="NO-ETHTOOL-RESET" notes="mlx5_coredoes not support reset via ethtool">
          <result value="SKIPPED">
            <verdict>ETHTOOL_RESET is not supported</verdict>
          </result>
        </results>
        <results tags="virtio-pci" key="NO-ETHTOOL-RESET" notes="VirtIO net does not support reset via ethtool">
          <result value="SKIPPED">
            <verdict>ETHTOOL_RESET is not supported</verdict>
          </result>
        </results>
      </iter>
      <iter result="PASSED">
        <arg name="env"/>
        <arg name="flag">SHARED_MAC|SHARED_PHY</arg>
        <arg name="sock_type"/>
        <arg name="if_down">FALSE</arg>
        <notes/>
        <results tags="i40e" key="NO-ETHTOOL-RESET" notes="intel/i40e does not support reset via ethtool">
          <result value="SKIPPED">
            <verdict>ETHTOOL_RESET is not supported</verdict>
          </result>
        </results>
        <results tags="ice" key="NO-ETHTOOL-RESET" notes="intel/ice does not support reset via ethtool">
          <result value="SKIPPED">
            <verdict>ETHTOOL_RESET is not supported</verdict>
          </result>
        </results>
        <results tags="igb" key="NO-ETHTOOL-RESET" notes="igb does not support reset via ethtool">
          <result value="SKIPPED">
            <verdict>ETHTOOL_RESET is not supported</verdict>
          </result>
        </results>
        <results tags="mlx5_core" key="NO-ETHTOOL-RESET" notes="mlx5_coredoes not support reset via ethtool">
          <result value="SKIPPED">
            <verdict>ETHTOOL_RESET is not supported</verdict>
          </result>
        </results>
        <results tags="virtio-pci" key="NO-ETHTOOL-RESET" notes="VirtIO net does not support reset via ethtool">
          <result value="SKIPPED">
            <verdict>ETHTOOL_RESET is not supported</verdict>
          </result>
        </results>
      </iter>
      <iter result="PASSED">
        <arg name="env"/>
        <arg name="flag">SHARED_MAC|SHARED_PHY</arg>
        <arg name="sock_type"/>
        <arg name="if_down">TRUE</arg>
        <notes/>
        <results tags="i40e" key="NO-ETHTOOL-RESET" notes="intel/i40e does not support reset via ethtool">
          <result value="SKIPPED">
            <verdict>ETHTOOL_RESET is not supported</verdict>
          </result>
        </results>
        <results tags="ice" key="NO-ETHTOOL-RESET" notes="intel/ice does not support reset via ethtool">
          <result value="SKIPPED">
            <verdict>ETHTOOL_RESET is not supported</verdict>
          </result>
        </results>
        <results tags="mlx5_core" key="NO-ETHTOOL-RESET" notes="mlx5_coredoes not support reset via ethtool">
          <result value="SKIPPED">
            <verdict>ETHTOOL_RESET is not supported</verdict>
          </result>
        </results>
        <results tags="igb" key="NO-ETHTOOL-RESET" notes="igb does not support reset via ethtool">
          <result value="SKIPPED">
            <verdict>ETHTOOL_RESET is not supported</verdict>
          </result>
        </results>
        <results tags="virtio-pci" key="NO-ETHTOOL-RESET" notes="VirtIO net does not support reset via ethtool">
          <result value="SKIPPED">
            <verdict>ETHTOOL_RESET is not supported</verdict>
          </result>
        </results>
      </iter>
      <iter result="PASSED">
        <arg name="env"/>
        <arg name="flag">ALL</arg>
        <arg name="sock_type"/>
        <arg name="if_down">FALSE</arg>
        <notes/>
        <results tags="i40e" key="NO-ETHTOOL-RESET" notes="intel/i40e does not support reset via ethtool">
          <result value="SKIPPED">
            <verdict>ETHTOOL_RESET is not supported</verdict>
          </result>
        </results>
        <results tags="ice" key="NO-ETHTOOL-RESET" notes="intel/ice does not support reset via ethtool">
          <result value="SKIPPED">
            <verdict>ETHTOOL_RESET is not supported</verdict>
          </result>
        </results>
        <results tags="igb" key="NO-ETHTOOL-RESET" notes="igb does not support reset via ethtool">
          <result value="SKIPPED">
            <verdict>ETHTOOL_RESET is not supported</verdict>
          </result>
        </results>
        <results tags="mlx5_core" key="NO-ETHTOOL-RESET" notes="mlx5_coredoes not support reset via ethtool">
          <result value="SKIPPED">
            <verdict>ETHTOOL_RESET is not supported</verdict>
          </result>
        </results>
        <results tags="virtio-pci" key="NO-ETHTOOL-RESET" notes="VirtIO net does not support reset via ethtool">
          <result value="SKIPPED">
            <verdict>ETHTOOL_RESET is not supported</verdict>
          </result>
        </results>
        <results tags="xilinx_efct" key="X3-1105" notes="On X3 sometimes in_errors isn't zeroed">
          <result value="PASSED"/>
          <result value="PASSED">
            <verdict>Interface statistic in_errors was not zeroed</verdict>
          </result>
        </results>
      </iter>
      <iter result="PASSED">
        <arg name="env"/>
        <arg name="flag">ALL</arg>
        <arg name="sock_type"/>
        <arg name="if_down">TRUE</arg>
        <notes/>
        <results tags="i40e" key="NO-ETHTOOL-RESET" notes="intel/i40e does not support reset via ethtool">
          <result value="SKIPPED">
            <verdict>ETHTOOL_RESET is not supported</verdict>
          </result>
        </results>
        <results tags="ice" key="NO-ETHTOOL-RESET" notes="intel/ice does not support reset via ethtool">
          <result value="SKIPPED">
            <verdict>ETHTOOL_RESET is not supported</verdict>
          </result>
        </results>
        <results tags="mlx5_core" key="NO-ETHTOOL-RESET" notes="mlx5_coredoes not support reset via ethtool">
          <result value="SKIPPED">
            <verdict>ETHTOOL_RESET is not supported</verdict>
          </result>
        </results>
        <results tags="igb" key="NO-ETHTOOL-RESET" notes="igb does not support reset via ethtool">
          <result value="SKIPPED">
            <verdict>ETHTOOL_RESET is not supported</verdict>
          </result>
        </results>
        <results tags="virtio-pci" key="NO-ETHTOOL-RESET" notes="VirtIO net does not support reset via ethtool">
          <result value="SKIPPED">
            <verdict>ETHTOOL_RESET is not supported</verdict>
          </result>
        </results>
        <results tags="xilinx_efct" key="X3-1105" notes="On X3 sometimes in_errors isn't zeroed">
          <result value="PASSED"/>
          <result value="PASSED">
            <verdict>Interface statistic in_errors was not zeroed</verdict>
          </result>
        </results>
      </iter>
    </test>
    <test name="mac_change_tx" type="script">
      <objective>Check that MAC address can be changed and it affects source MAC address of sent packets.</objective>
      <notes/>
      <iter result="PASSED">
        <arg name="env"/>
        <arg name="if_down"/>
        <notes/>
      </iter>
    </test>
    <test name="mac_change_rx" type="script">
      <objective>Check that MAC address can be changed and after that packets sent to the new address can be received.</objective>
      <notes/>
      <iter result="PASSED">
        <arg name="env"/>
        <arg name="promisc"/>
        <notes/>
      </iter>
    </test>
    <test name="ping" type="script">
      <objective>Check that ping tool can ping Tester address from IUT.</objective>
      <notes/>
      <iter result="PASSED">
        <arg name="env"/>
        <arg name="packets"/>
        <arg name="data_size"/>
        <arg name="interval"/>
        <notes/>
      </iter>
    </test>
    <test name="read_sysfs" type="script">
      <objective>Check that the files in sysfs related to the tested driver can be read.</objective>
      <notes/>
      <iter result="PASSED">
        <arg name="env"/>
        <notes/>
        <results tags="sfc_ef100" key="NET-49" notes="sfc_ef100 uses sfc name in debugfs">
          <result value="FAILED">
            <verdict>driver/interface subdirectory cannot be opened in /sys/kernel/debug/</verdict>
          </result>
        </results>
        <results tags="i40e" key="NO-SYSFS-DEBUG" notes="intel/i40e does not provide debug in sysfs">
          <result value="FAILED">
            <verdict>driver/interface subdirectory cannot be opened in /sys/kernel/debug/</verdict>
          </result>
        </results>
        <results tags="ice" key="NO-SYSFS-DEBUG" notes="ice does not provide debug in sysfs">
          <result value="FAILED">
            <verdict>driver/interface subdirectory cannot be opened in /sys/kernel/debug/</verdict>
          </result>
        </results>
        <results tags="igb" key="NO-SYSFS-DEBUG" notes="igb does not provide debug in sysfs">
          <result value="FAILED">
            <verdict>driver/interface subdirectory cannot be opened in /sys/kernel/debug/</verdict>
          </result>
        </results>
        <results tags="mlx5_core" key="NO-SYSFS-DEBUG" notes="mlx5_core does not provide debug in sysfs, it uses mlx5 instead">
          <result value="FAILED">
            <verdict>driver/interface subdirectory cannot be opened in /sys/kernel/debug/</verdict>
          </result>
        </results>
        <results tags="virtio-pci" key="NO-SYSFS-DEBUG" notes="VirtIO net does not provide debug in sysfs">
          <result value="FAILED">
            <verdict>driver/interface subdirectory cannot be opened in /sys/kernel/debug/</verdict>
          </result>
        </results>
      </iter>
    </test>
    <test name="mtu_tcp" type="script">
      <objective>Check that TCP packets of full MTU size are sent and processed correctly.</objective>
      <notes/>
      <iter result="PASSED">
        <arg name="env"/>
        <arg name="mtu">576</arg>
        <arg name="tx"/>
        <arg name="gso_on"/>
        <arg name="tso_on">FALSE</arg>
        <arg name="pkt_size"/>
        <arg name="sends_num"/>
        <notes/>
      </iter>
      <iter result="PASSED">
        <arg name="env">VAR.env.peer2peer</arg>
        <arg name="mtu">576</arg>
        <arg name="tx"/>
        <arg name="gso_on"/>
        <arg name="tso_on">TRUE</arg>
        <arg name="pkt_size"/>
        <arg name="sends_num"/>
        <notes/>
        <results tags="xilinx_efct" key="NO-TSO" notes="TCP segmentation offload will not be implemented: XN-200494-PD-1D/KD-070">
          <result value="SKIPPED">
            <verdict>Feature 'tx-tcp-segmentation' is disabled and cannot be modified</verdict>
          </result>
        </results>
      </iter>
      <iter result="PASSED">
        <arg name="env">VAR.env.peer2peer_ipv6</arg>
        <arg name="mtu">576</arg>
        <arg name="tx"/>
        <arg name="gso_on"/>
        <arg name="tso_on">TRUE</arg>
        <arg name="pkt_size"/>
        <arg name="sends_num"/>
        <notes/>
        <results tags="ice&amp;linux-mm&lt;508" key="TSO6">
          <result value="SKIPPED">
            <verdict>Feature 'tx-tcp6-segmentation' is disabled and cannot be modified</verdict>
          </result>
        </results>
        <results tags="xilinx_efct" key="NO-TSO" notes="TCP segmentation offload will not be implemented: XN-200494-PD-1D/KD-070">
          <result value="SKIPPED">
            <verdict>Feature 'tx-tcp6-segmentation' is disabled and cannot be modified</verdict>
          </result>
        </results>
      </iter>
      <iter result="PASSED">
        <arg name="env"/>
        <arg name="mtu">1280</arg>
        <arg name="tx"/>
        <arg name="gso_on"/>
        <arg name="tso_on">FALSE</arg>
        <arg name="pkt_size"/>
        <arg name="sends_num"/>
        <notes/>
      </iter>
      <iter result="PASSED">
        <arg name="env">VAR.env.peer2peer</arg>
        <arg name="mtu">1280</arg>
        <arg name="tx"/>
        <arg name="gso_on"/>
        <arg name="tso_on">TRUE</arg>
        <arg name="pkt_size"/>
        <arg name="sends_num"/>
        <notes/>
        <results tags="xilinx_efct" key="NO-TSO" notes="TCP segmentation offload will not be implemented: XN-200494-PD-1D/KD-070">
          <result value="SKIPPED">
            <verdict>Feature 'tx-tcp-segmentation' is disabled and cannot be modified</verdict>
          </result>
        </results>
      </iter>
      <iter result="PASSED">
        <arg name="env">VAR.env.peer2peer_ipv6</arg>
        <arg name="mtu">1280</arg>
        <arg name="tx"/>
        <arg name="gso_on"/>
        <arg name="tso_on">TRUE</arg>
        <arg name="pkt_size"/>
        <arg name="sends_num"/>
        <notes/>
        <results tags="ice&amp;linux-mm&lt;508" key="TSO6">
          <result value="SKIPPED">
            <verdict>Feature 'tx-tcp6-segmentation' is disabled and cannot be modified</verdict>
          </result>
        </results>
        <results tags="xilinx_efct" key="NO-TSO" notes="TCP segmentation offload will not be implemented: XN-200494-PD-1D/KD-070">
          <result value="SKIPPED">
            <verdict>Feature 'tx-tcp6-segmentation' is disabled and cannot be modified</verdict>
          </result>
        </results>
      </iter>
      <iter result="PASSED">
        <arg name="env"/>
        <arg name="mtu">1500</arg>
        <arg name="tx"/>
        <arg name="gso_on"/>
        <arg name="tso_on">FALSE</arg>
        <arg name="pkt_size"/>
        <arg name="sends_num"/>
        <notes/>
      </iter>
      <iter result="PASSED">
        <arg name="env">VAR.env.peer2peer</arg>
        <arg name="mtu">1500</arg>
        <arg name="tx"/>
        <arg name="gso_on"/>
        <arg name="tso_on">TRUE</arg>
        <arg name="pkt_size"/>
        <arg name="sends_num"/>
        <notes/>
        <results tags="xilinx_efct" key="NO-TSO" notes="TCP segmentation offload will not be implemented: XN-200494-PD-1D/KD-070">
          <result value="SKIPPED">
            <verdict>Feature 'tx-tcp-segmentation' is disabled and cannot be modified</verdict>
          </result>
        </results>
      </iter>
      <iter result="PASSED">
        <arg name="env">VAR.env.peer2peer_ipv6</arg>
        <arg name="mtu">1500</arg>
        <arg name="tx"/>
        <arg name="gso_on"/>
        <arg name="tso_on">TRUE</arg>
        <arg name="pkt_size"/>
        <arg name="sends_num"/>
        <notes/>
        <results tags="ice&amp;linux-mm&lt;508" key="TSO6">
          <result value="SKIPPED">
            <verdict>Feature 'tx-tcp6-segmentation' is disabled and cannot be modified</verdict>
          </result>
        </results>
        <results tags="xilinx_efct" key="NO-TSO" notes="TCP segmentation offload will not be implemented: XN-200494-PD-1D/KD-070">
          <result value="SKIPPED">
            <verdict>Feature 'tx-tcp6-segmentation' is disabled and cannot be modified</verdict>
          </result>
        </results>
      </iter>
      <iter result="PASSED">
        <arg name="env"/>
        <arg name="mtu">1600</arg>
        <arg name="tx"/>
        <arg name="gso_on"/>
        <arg name="tso_on">FALSE</arg>
        <arg name="pkt_size"/>
        <arg name="sends_num"/>
        <notes/>
        <results tags="xilinx-virtio-net" key="XILINX-VIRTIO-MTU" notes="Xilinx VirtIO net does not allow MTU change">
          <result value="FAILED">
            <verdict>Failed to set MTU on IUT, rc=TA_UNIX-EINVAL</verdict>
          </result>
        </results>
      </iter>
      <iter result="PASSED">
        <arg name="env">VAR.env.peer2peer</arg>
        <arg name="mtu">1600</arg>
        <arg name="tx"/>
        <arg name="gso_on"/>
        <arg name="tso_on">TRUE</arg>
        <arg name="pkt_size"/>
        <arg name="sends_num"/>
        <notes/>
        <results tags="xilinx-virtio-net" key="XILINX-VIRTIO-MTU" notes="Xilinx VirtIO net does not allow MTU change">
          <result value="FAILED">
            <verdict>Failed to set MTU on IUT, rc=TA_UNIX-EINVAL</verdict>
          </result>
        </results>
        <results tags="xilinx_efct" key="NO-TSO" notes="TCP segmentation offload will not be implemented: XN-200494-PD-1D/KD-070">
          <result value="SKIPPED">
            <verdict>Feature 'tx-tcp-segmentation' is disabled and cannot be modified</verdict>
          </result>
        </results>
      </iter>
      <iter result="PASSED">
        <arg name="env">VAR.env.peer2peer_ipv6</arg>
        <arg name="mtu">1600</arg>
        <arg name="tx"/>
        <arg name="gso_on"/>
        <arg name="tso_on">TRUE</arg>
        <arg name="pkt_size"/>
        <arg name="sends_num"/>
        <notes/>
        <results tags="ice&amp;linux-mm&lt;508" key="TSO6">
          <result value="SKIPPED">
            <verdict>Feature 'tx-tcp6-segmentation' is disabled and cannot be modified</verdict>
          </result>
        </results>
        <results tags="xilinx-virtio-net" key="XILINX-VIRTIO-MTU" notes="Xilinx VirtIO net does not allow MTU change">
          <result value="FAILED">
            <verdict>Failed to set MTU on IUT, rc=TA_UNIX-EINVAL</verdict>
          </result>
        </results>
        <results tags="xilinx_efct" key="NO-TSO" notes="TCP segmentation offload will not be implemented: XN-200494-PD-1D/KD-070">
          <result value="SKIPPED">
            <verdict>Feature 'tx-tcp6-segmentation' is disabled and cannot be modified</verdict>
          </result>
        </results>
      </iter>
      <iter result="PASSED">
        <arg name="env">VAR.env.peer2peer_ipv6</arg>
        <arg name="mtu">1948</arg>
        <arg name="tx"/>
        <arg name="gso_on"/>
        <arg name="tso_on">FALSE</arg>
        <arg name="pkt_size"/>
        <arg name="sends_num"/>
        <notes/>
      </iter>
      <iter result="PASSED">
        <arg name="env">VAR.env.peer2peer</arg>
        <arg name="mtu">1948</arg>
        <arg name="tx"/>
        <arg name="gso_on"/>
        <arg name="tso_on">FALSE</arg>
        <arg name="pkt_size"/>
        <arg name="sends_num"/>
        <notes/>
      </iter>
      <iter result="PASSED">
        <arg name="env">VAR.env.peer2peer_ipv6</arg>
        <arg name="mtu">1948</arg>
        <arg name="tx"/>
        <arg name="gso_on"/>
        <arg name="tso_on">TRUE</arg>
        <arg name="pkt_size"/>
        <arg name="sends_num"/>
        <notes/>
        <results tags="xilinx_efct" key="NO-TSO" notes="TCP segmentation offload will not be implemented: XN-200494-PD-1D/KD-070">
          <result value="SKIPPED">
            <verdict>Feature 'tx-tcp6-segmentation' is disabled and cannot be modified</verdict>
          </result>
        </results>
      </iter>
      <iter result="PASSED">
        <arg name="env">VAR.env.peer2peer</arg>
        <arg name="mtu">1948</arg>
        <arg name="tx"/>
        <arg name="gso_on"/>
        <arg name="tso_on">TRUE</arg>
        <arg name="pkt_size"/>
        <arg name="sends_num"/>
        <notes/>
        <results tags="xilinx_efct" key="NO-TSO" notes="TCP segmentation offload will not be implemented: XN-200494-PD-1D/KD-070">
          <result value="SKIPPED">
            <verdict>Feature 'tx-tcp-segmentation' is disabled and cannot be modified</verdict>
          </result>
        </results>
        <results tags="ice&amp;linux-mm&lt;508" key="TSO6">
          <result value="SKIPPED">
            <verdict>Feature 'tx-tcp6-segmentation' is disabled and cannot be modified</verdict>
          </result>
        </results>
      </iter>
      <iter result="PASSED">
        <arg name="env">VAR.env.peer2peer</arg>
        <arg name="mtu">9000</arg>
        <arg name="tx"/>
        <arg name="gso_on"/>
        <arg name="tso_on">FALSE</arg>
        <arg name="pkt_size"/>
        <arg name="sends_num"/>
        <notes/>
        <results tags="xilinx-virtio-net" key="XILINX-VIRTIO-MTU" notes="Xilinx VirtIO net does not allow MTU change">
          <result value="FAILED">
            <verdict>Failed to set MTU on IUT, rc=TA_UNIX-EINVAL</verdict>
          </result>
        </results>
        <results tags="xilinx_efct" key="NET-44, NET-80" notes="X3 NIC: MTU can be configured to be between 576 and 1948 bytes">
          <result value="FAILED">
            <verdict>Failed to set MTU on IUT, rc=TA_UNIX-EINVAL</verdict>
          </result>
        </results>
      </iter>
      <iter result="PASSED">
        <arg name="env">VAR.env.peer2peer_ipv6</arg>
        <arg name="mtu">9000</arg>
        <arg name="tx"/>
        <arg name="gso_on"/>
        <arg name="tso_on">FALSE</arg>
        <arg name="pkt_size"/>
        <arg name="sends_num"/>
        <notes/>
        <results tags="xilinx-virtio-net" key="XILINX-VIRTIO-MTU" notes="Xilinx VirtIO net does not allow MTU change">
          <result value="FAILED">
            <verdict>Failed to set MTU on IUT, rc=TA_UNIX-EINVAL</verdict>
          </result>
        </results>
        <results tags="xilinx_efct" key="NET-44, NET-80" notes="X3 NIC: MTU can be configured to be between 576 and 1948 bytes">
          <result value="FAILED">
            <verdict>Failed to set MTU on IUT, rc=TA_UNIX-EINVAL</verdict>
          </result>
        </results>
      </iter>
      <iter result="PASSED">
        <arg name="env">VAR.env.peer2peer</arg>
        <arg name="mtu">9000</arg>
        <arg name="tx"/>
        <arg name="gso_on"/>
        <arg name="tso_on">TRUE</arg>
        <arg name="pkt_size"/>
        <arg name="sends_num"/>
        <notes/>
        <results tags="xilinx-virtio-net" key="XILINX-VIRTIO-MTU" notes="Xilinx VirtIO net does not allow MTU change">
          <result value="FAILED">
            <verdict>Failed to set MTU on IUT, rc=TA_UNIX-EINVAL</verdict>
          </result>
        </results>
        <results tags="xilinx_efct" key="NET-44, NET-80" notes="X3 NIC: MTU can be configured to be between 576 and 1948 bytes">
          <result value="FAILED">
            <verdict>Failed to set MTU on IUT, rc=TA_UNIX-EINVAL</verdict>
          </result>
        </results>
      </iter>
      <iter result="PASSED">
        <arg name="env">VAR.env.peer2peer_ipv6</arg>
        <arg name="mtu">9000</arg>
        <arg name="tx"/>
        <arg name="gso_on"/>
        <arg name="tso_on">TRUE</arg>
        <arg name="pkt_size"/>
        <arg name="sends_num"/>
        <notes/>
        <results tags="ice&amp;linux-mm&lt;508" key="TSO6">
          <result value="SKIPPED">
            <verdict>Feature 'tx-tcp6-segmentation' is disabled and cannot be modified</verdict>
          </result>
        </results>
        <results tags="xilinx-virtio-net" key="XILINX-VIRTIO-MTU" notes="Xilinx VirtIO net does not allow MTU change">
          <result value="FAILED">
            <verdict>Failed to set MTU on IUT, rc=TA_UNIX-EINVAL</verdict>
          </result>
        </results>
        <results tags="xilinx_efct" key="NET-44, NET-80" notes="X3 NIC: MTU can be configured to be between 576 and 1948 bytes">
          <result value="FAILED">
            <verdict>Failed to set MTU on IUT, rc=TA_UNIX-EINVAL</verdict>
          </result>
        </results>
      </iter>
    </test>
    <test name="mtu_udp" type="script">
      <objective>Check that UDP packets of full MTU size are sent and that jumbo frames are processed correctly.</objective>
      <notes/>
      <iter result="PASSED">
        <arg name="env"/>
        <arg name="mtu">576</arg>
        <arg name="tx"/>
        <arg name="pkt_size"/>
        <arg name="sends_num"/>
        <notes/>
      </iter>
      <iter result="PASSED">
        <arg name="env"/>
        <arg name="mtu">1280</arg>
        <arg name="tx"/>
        <arg name="pkt_size"/>
        <arg name="sends_num"/>
        <notes/>
      </iter>
      <iter result="PASSED">
        <arg name="env"/>
        <arg name="mtu">1500</arg>
        <arg name="tx"/>
        <arg name="pkt_size"/>
        <arg name="sends_num"/>
        <notes/>
      </iter>
      <iter result="PASSED">
        <arg name="env"/>
        <arg name="mtu">1600</arg>
        <arg name="tx"/>
        <arg name="pkt_size"/>
        <arg name="sends_num"/>
        <notes/>
        <results tags="xilinx-virtio-net" key="XILINX-VIRTIO-MTU" notes="Xilinx VirtIO net does not allow MTU change">
          <result value="FAILED">
            <verdict>Failed to set MTU on IUT, rc=TA_UNIX-EINVAL</verdict>
          </result>
        </results>
      </iter>
      <iter result="PASSED">
        <arg name="env"/>
        <arg name="mtu">1948</arg>
        <arg name="tx"/>
        <arg name="pkt_size"/>
        <arg name="sends_num"/>
        <notes/>
      </iter>
      <iter result="PASSED">
        <arg name="env"/>
        <arg name="mtu">9000</arg>
        <arg name="tx"/>
        <arg name="pkt_size"/>
        <arg name="sends_num"/>
        <notes/>
        <results tags="xilinx-virtio-net" key="XILINX-VIRTIO-MTU" notes="Xilinx VirtIO net does not allow MTU change">
          <result value="FAILED">
            <verdict>Failed to set MTU on IUT, rc=TA_UNIX-EINVAL</verdict>
          </result>
        </results>
        <results tags="xilinx_efct" key="NET-44" notes="X3 NIC: MTU can be configured to be between 576 and 1960 bytes">
          <result value="FAILED">
            <verdict>Failed to set MTU on IUT, rc=TA_UNIX-EINVAL</verdict>
          </result>
        </results>
      </iter>
    </test>
    <test name="send_receive" type="script">
      <objective>Check that packets can be sent and received over the tested interface.</objective>
      <notes/>
      <iter result="PASSED">
        <arg name="env"/>
        <arg name="sock_type"/>
        <arg name="tx"/>
        <arg name="pkt_size"/>
        <arg name="pkts_num"/>
        <notes/>
      </iter>
    </test>
    <test name="set_if_down" type="script">
      <objective>Check that network interface can be set DOWN.</objective>
      <notes/>
      <iter result="PASSED">
        <arg name="env"/>
        <arg name="check_socket">FALSE</arg>
        <notes/>
      </iter>
      <iter result="PASSED">
        <arg name="env"/>
        <arg name="check_socket">TRUE</arg>
        <notes/>
        <results tags="sfc_ef100" key="SWNETLINUX-4591" notes="UDP send in interface down state is delivered">
          <result value="FAILED">
            <verdict>Tester receives data sent after IUT interface was set DOWN</verdict>
          </result>
        </results>
      </iter>
    </test>
    <test name="multicast" type="script">
      <objective>Check that multicast packets may be sent and received over the tested interface.</objective>
      <notes/>
      <iter result="PASSED">
        <arg name="env"/>
        <arg name="tx"/>
        <arg name="sends_num"/>
        <notes/>
        <results tags="sfc_ef100" key="SWNETLINUX-4592" notes="UDP multicast is not received">
          <result value="FAILED">
            <verdict>Checking multicast sending: receiver did not become readable</verdict>
          </result>
        </results>
      </iter>
    </test>
    <test name="set_rx_headroom" type="script">
      <objective>Check ndo_set_rx_headroom callback</objective>
      <notes/>
      <iter result="PASSED">
        <arg name="env"/>
        <arg name="if_down_up"/>
        <notes/>
        <results tags="mlx5_core" key="NO-ETHTOOL-MSGLVL" notes="mlx5 does not support message level change via ethtool">
          <result value="PASSED">
            <verdict>Failed to enable all flags in msglvl</verdict>
          </result>
        </results>
        <results tags="virtio-pci" key="NO-ETHTOOL-MSGLVL" notes="VirtIO net does not support message level change via ethtool">
          <result value="PASSED">
            <verdict>Failed to enable all flags in msglvl</verdict>
          </result>
        </results>
        <results tags="iut-no-tun" key="NO-TUN">
          <result value="SKIPPED">
            <verdict>TUN/TAP is unavailable</verdict>
          </result>
        </results>
      </iter>
    </test>
  </iter>
</test>
